TAREAS/Test_perifericos/Contador_unos/control_contador.v
module control_contador ( clk, rst, init, R_LSB, END, LOAD, SHIFT, ADD_UNOS, ADD_BITS, DONE );

   input    clk;
   input    rst;
   input    init;
   input    END;
   input    R_LSB;

   output reg  LOAD;
   output reg  SHIFT;
   output reg  ADD_BITS;
   output reg  ADD_UNOS;
   output reg  DONE;

   parameter START        = 3'b000;
   parameter CHECK        = 3'b001;
   parameter ADD_C_UNOS   = 3'b010;
   parameter ADD_C_BITS   = 3'b011;
   parameter FIN          = 3'b100;
 
   reg [2:0] state;

 initial begin
   state = START;

   DONE       = 0;
   LOAD       = 0;
   SHIFT      = 0;
   ADD_UNOS = 0;
   ADD_BITS = 0;
  end

 always @(posedge clk) begin
   if (rst) begin
      state <= START;
   end
   
   else begin

 case(state)
  START:begin
    if(init)
     state <= CHECK;
    else
     state <= START;
  end

  CHECK:begin
    if(R_LSB)
     state <= ADD_C_UNOS;
    else
     state <= ADD_C_BITS;
    end

  ADD_C_UNOS:begin
     state <= ADD_C_BITS;
    end

  ADD_C_BITS:begin
    if(END)
     state <= FIN;
    else
     state <= CHECK;
  end

  FIN: begin
    state <= START;
  end

  default:
     state <= START;
 endcase
 
 end

 end


 always @(state) begin
     DONE     = 0;
     LOAD     = 0;
     SHIFT    = 0;
     ADD_UNOS = 0;
     ADD_BITS = 0;

  case(state)

   START:begin
     LOAD     = 1;
    end

   CHECK:begin
    
    end
   
   ADD_C_UNOS:begin
     ADD_UNOS  = 1;
    end
 
   ADD_C_BITS:begin
     SHIFT     = 1;
     ADD_BITS  = 1;
    end
  
   FIN:begin
     DONE      = 1;
   end

   default: begin
     DONE       = 0;
     LOAD       = 0;
     SHIFT      = 0;
     ADD_UNOS = 0;
     ADD_BITS = 0;
    end

  endcase

  end

endmodule

TAREAS/Test_perifericos/Contador_unos/control_contador_TB.v
`timescale 1ns / 1ps
`define SIMULATION

module control_contador_TB;

reg clk;
reg rst;
reg init;
reg R_LSB;
reg END;

wire LOAD;
wire SHIFT;
wire ADD_UNOS;
wire ADD_BITS;
wire DONE;

control_contador uut( .clk(clk), .rst(rst), .init(init), .R_LSB(R_LSB), .END(END), .LOAD(LOAD), .SHIFT(SHIFT),
    .ADD_UNOS(ADD_UNOS), .ADD_BITS(ADD_BITS), .DONE(DONE));

parameter PERIOD = 20;
parameter real DUTY_CYCLE = 0.5;
parameter OFFSET = 0;

initial begin

    #OFFSET;

    forever begin

        clk = 0;
        #(PERIOD-(PERIOD*DUTY_CYCLE));

        clk = 1;
        #(PERIOD*DUTY_CYCLE);

    end

end

initial begin

    rst = 1;
    init = 0;
    R_LSB = 0;
    END = 0;

    @(negedge clk);
    rst = 0;

    // START -> CHECK
    @(negedge clk);
    init = 1;

    // CHECK -> ADD_C_UNOS
    @(negedge clk);
    R_LSB = 1;

    // ADD_C_BITS -> CHECK
    @(negedge clk);
    END = 0;

    // CHECK -> ADD_C_BITS
    @(negedge clk);
    R_LSB = 0;

    // ADD_C_BITS -> FIN
    @(negedge clk);
    END = 1;

    #(100);

    $finish;

end

   initial begin: TEST_CASE
        $dumpfile("control_contador_TB.vcd");
        $dumpvars(-1, uut);
        #(10000) $finish;
    end

endmodule

TAREAS/Test_perifericos/Contador_unos/control_contador_TB.vcd
$date
	Thu Jul 16 10:37:56 2026
$end
$version
	Icarus Verilog
$end
$timescale
	1ps
$end
$scope module control_contador_TB $end
$scope module uut $end
$var wire 1 ! END $end
$var wire 1 " R_LSB $end
$var wire 1 # clk $end
$var wire 1 $ init $end
$var wire 1 % rst $end
$var parameter 3 & ADD_C_BITS $end
$var parameter 3 ' ADD_C_UNOS $end
$var parameter 3 ( CHECK $end
$var parameter 3 ) FIN $end
$var parameter 3 * START $end
$var reg 1 + ADD_BITS $end
$var reg 1 , ADD_UNOS $end
$var reg 1 - DONE $end
$var reg 1 . LOAD $end
$var reg 1 / SHIFT $end
$var reg 3 0 state [2:0] $end
$upscope $end
$upscope $end
$enddefinitions $end
$comment Show the parameter values. $end
$dumpall
b0 *
b100 )
b1 (
b10 '
b11 &
$end
#0
$dumpvars
b0 0
0/
1.
0-
0,
0+
0%
0$
0#
0"
0!
$end
#10000
1#
#20000
1$
0#
#30000
0.
b1 0
1#
#40000
1"
0#
#50000
1,
b10 0
1#
#60000
0#
#70000
1+
1/
0,
b11 0
1#
#80000
0"
0#
#90000
0+
0/
b1 0
1#
#100000
1!
0#
#110000
1+
1/
b11 0
1#
#120000
0#
#130000
1-
0+
0/
b100 0
1#
#140000
0#
#150000
1.
0-
b0 0
1#
#160000
0#
#170000
0.
b1 0
1#
#180000
0#
#190000
1+
1/
b11 0
1#
